{
  "per_player": {
    "1": {
      "team": "Team A",
      "distance_m": 121.66,
      "top_speed_ms": 11.99,
      "avg_speed_ms": 4.28,
      "possession_s": 0.4,
      "passes_made": 1,
      "passes_received": 0,
      "interceptions": 1
    },
    "2": {
      "team": "Team B",
      "distance_m": 147.61,
      "top_speed_ms": 11.96,
      "avg_speed_ms": 5.37,
      "possession_s": 4.76,
      "passes_made": 4,
      "passes_received": 1,
      "interceptions": 3
    },
    "3": {
      "team": "Team A",
      "distance_m": 97.02,
      "top_speed_ms": 11.98,
      "avg_speed_ms": 3.42,
      "possession_s": 1.88,
      "passes_made": 2,
      "passes_received": 1,
      "interceptions": 1
    },
    "4": {
      "team": "Team A",
      "distance_m": 128.85,
      "top_speed_ms": 11.9,
      "avg_speed_ms": 4.58,
      "possession_s": 3.76,
      "passes_made": 2,
      "passes_received": 1,
      "interceptions": 0
    },
    "5": {
      "team": "Team B",
      "distance_m": 111.97,
      "top_speed_ms": 11.75,
      "avg_speed_ms": 3.78,
      "possession_s": 0.48,
      "passes_made": 1,
      "passes_received": 0,
      "interceptions": 1
    },
    "6": {
      "team": "Team B",
      "distance_m": 25.36,
      "top_speed_ms": 11.56,
      "avg_speed_ms": 2.4,
      "possession_s": 1.24,
      "passes_made": 5,
      "passes_received": 1,
      "interceptions": 4
    },
    "7": {
      "team": "Team A",
      "distance_m": 106.9,
      "top_speed_ms": 11.98,
      "avg_speed_ms": 3.63,
      "possession_s": 0.0,
      "passes_made": 0,
      "passes_received": 0,
      "interceptions": 0
    },
    "8": {
      "team": "Team A",
      "distance_m": 106.46,
      "top_speed_ms": 12.0,
      "avg_speed_ms": 3.71,
      "possession_s": 0.52,
      "passes_made": 1,
      "passes_received": 0,
      "interceptions": 0
    },
    "9": {
      "team": "Team A",
      "distance_m": 126.54,
      "top_speed_ms": 11.95,
      "avg_speed_ms": 4.36,
      "possession_s": 0.0,
      "passes_made": 0,
      "passes_received": 0,
      "interceptions": 0
    },
    "10": {
      "team": "Team B",
      "distance_m": 115.56,
      "top_speed_ms": 11.75,
      "avg_speed_ms": 4.09,
      "possession_s": 2.68,
      "passes_made": 2,
      "passes_received": 1,
      "interceptions": 1
    },
    "11": {
      "team": "Team A",
      "distance_m": 129.73,
      "top_speed_ms": 11.99,
      "avg_speed_ms": 4.47,
      "possession_s": 0.24,
      "passes_made": 0,
      "passes_received": 1,
      "interceptions": 0
    },
    "12": {
      "team": "Team A",
      "distance_m": 113.08,
      "top_speed_ms": 11.92,
      "avg_speed_ms": 4.07,
      "possession_s": 0.0,
      "passes_made": 0,
      "passes_received": 0,
      "interceptions": 0
    },
    "13": {
      "team": "Team A",
      "distance_m": 106.81,
      "top_speed_ms": 12.0,
      "avg_speed_ms": 3.82,
      "possession_s": 1.24,
      "passes_made": 2,
      "passes_received": 1,
      "interceptions": 2
    },
    "14": {
      "team": "Team A",
      "distance_m": 91.39,
      "top_speed_ms": 11.83,
      "avg_speed_ms": 4.5,
      "possession_s": 3.28,
      "passes_made": 3,
      "passes_received": 0,
      "interceptions": 3
    },
    "15": {
      "team": "Referee",
      "distance_m": 109.74,
      "top_speed_ms": 11.97,
      "avg_speed_ms": 3.94,
      "possession_s": 0.72,
      "passes_made": 0,
      "passes_received": 0,
      "interceptions": 0
    },
    "16": {
      "team": "Team A",
      "distance_m": 133.17,
      "top_speed_ms": 11.71,
      "avg_speed_ms": 4.64,
      "possession_s": 0.0,
      "passes_made": 0,
      "passes_received": 0,
      "interceptions": 0
    },
    "17": {
      "team": "Team A",
      "distance_m": 100.13,
      "top_speed_ms": 11.97,
      "avg_speed_ms": 4.34,
      "possession_s": 0.0,
      "passes_made": 0,
      "passes_received": 0,
      "interceptions": 0
    },
    "18": {
      "team": "Team B",
      "distance_m": 138.6,
      "top_speed_ms": 11.7,
      "avg_speed_ms": 4.75,
      "possession_s": 1.0,
      "passes_made": 4,
      "passes_received": 3,
      "interceptions": 1
    },
    "19": {
      "team": "Team A",
      "distance_m": 120.31,
      "top_speed_ms": 12.0,
      "avg_speed_ms": 4.11,
      "possession_s": 0.96,
      "passes_made": 2,
      "passes_received": 1,
      "interceptions": 1
    },
    "20": {
      "team": "Team B",
      "distance_m": 118.37,
      "top_speed_ms": 11.99,
      "avg_speed_ms": 4.09,
      "possession_s": 2.68,
      "passes_made": 4,
      "passes_received": 0,
      "interceptions": 3
    },
    "21": {
      "team": "Team B",
      "distance_m": 132.22,
      "top_speed_ms": 12.0,
      "avg_speed_ms": 4.48,
      "possession_s": 2.76,
      "passes_made": 6,
      "passes_received": 2,
      "interceptions": 4
    },
    "22": {
      "team": "Team B",
      "distance_m": 115.94,
      "top_speed_ms": 11.91,
      "avg_speed_ms": 3.97,
      "possession_s": 0.4,
      "passes_made": 0,
      "passes_received": 0,
      "interceptions": 1
    },
    "23": {
      "team": "Team A",
      "distance_m": 82.48,
      "top_speed_ms": 11.68,
      "avg_speed_ms": 3.47,
      "possession_s": 0.4,
      "passes_made": 0,
      "passes_received": 0,
      "interceptions": 0
    },
    "24": {
      "team": "Team B",
      "distance_m": 0.49,
      "top_speed_ms": 2.44,
      "avg_speed_ms": 1.75,
      "possession_s": 0.0,
      "passes_made": 0,
      "passes_received": 0,
      "interceptions": 0
    },
    "30": {
      "team": "Team A",
      "distance_m": 1.07,
      "top_speed_ms": 5.97,
      "avg_speed_ms": 3.83,
      "possession_s": 0.0,
      "passes_made": 0,
      "passes_received": 0,
      "interceptions": 0
    },
    "34": {
      "team": "Team B",
      "distance_m": 1.18,
      "top_speed_ms": 8.38,
      "avg_speed_ms": 7.36,
      "possession_s": 0.0,
      "passes_made": 0,
      "passes_received": 0,
      "interceptions": 0
    },
    "35": {
      "team": "Team B",
      "distance_m": 0.1,
      "top_speed_ms": 2.45,
      "avg_speed_ms": 2.45,
      "possession_s": 0.0,
      "passes_made": 0,
      "passes_received": 0,
      "interceptions": 0
    },
    "40": {
      "team": "Team B",
      "distance_m": 0.75,
      "top_speed_ms": 4.91,
      "avg_speed_ms": 2.69,
      "possession_s": 0.0,
      "passes_made": 0,
      "passes_received": 0,
      "interceptions": 0
    },
    "47": {
      "team": "Goalkeeper",
      "distance_m": 0.0,
      "top_speed_ms": 0.0,
      "avg_speed_ms": 0.0,
      "possession_s": 0.0,
      "passes_made": 0,
      "passes_received": 0,
      "interceptions": 0
    },
    "51": {
      "team": "Team B",
      "distance_m": 0.07,
      "top_speed_ms": 1.65,
      "avg_speed_ms": 1.65,
      "possession_s": 0.0,
      "passes_made": 0,
      "passes_received": 0,
      "interceptions": 0
    },
    "55": {
      "team": "Team B",
      "distance_m": 0.19,
      "top_speed_ms": 2.69,
      "avg_speed_ms": 2.34,
      "possession_s": 0.0,
      "passes_made": 0,
      "passes_received": 0,
      "interceptions": 0
    },
    "59": {
      "team": "Team B",
      "distance_m": 2.64,
      "top_speed_ms": 8.27,
      "avg_speed_ms": 5.5,
      "possession_s": 0.0,
      "passes_made": 0,
      "passes_received": 0,
      "interceptions": 0
    },
    "92": {
      "team": "Goalkeeper",
      "distance_m": 3.46,
      "top_speed_ms": 9.92,
      "avg_speed_ms": 6.18,
      "possession_s": 0.0,
      "passes_made": 0,
      "passes_received": 0,
      "interceptions": 0
    },
    "117": {
      "team": "Goalkeeper",
      "distance_m": 2.2,
      "top_speed_ms": 3.3,
      "avg_speed_ms": 1.41,
      "possession_s": 0.0,
      "passes_made": 0,
      "passes_received": 0,
      "interceptions": 0
    },
    "123": {
      "team": "Team A",
      "distance_m": 0.8,
      "top_speed_ms": 7.25,
      "avg_speed_ms": 3.32,
      "possession_s": 0.0,
      "passes_made": 0,
      "passes_received": 0,
      "interceptions": 0
    },
    "138": {
      "team": "Goalkeeper",
      "distance_m": 0.0,
      "top_speed_ms": 0.0,
      "avg_speed_ms": 0.0,
      "possession_s": 0.0,
      "passes_made": 0,
      "passes_received": 0,
      "interceptions": 0
    },
    "146": {
      "team": "Team B",
      "distance_m": 0.28,
      "top_speed_ms": 3.31,
      "avg_speed_ms": 2.32,
      "possession_s": 0.0,
      "passes_made": 0,
      "passes_received": 0,
      "interceptions": 0
    },
    "148": {
      "team": "Goalkeeper",
      "distance_m": 0.0,
      "top_speed_ms": 0.0,
      "avg_speed_ms": 0.0,
      "possession_s": 0.0,
      "passes_made": 0,
      "passes_received": 0,
      "interceptions": 0
    },
    "166": {
      "team": "Team B",
      "distance_m": 0.49,
      "top_speed_ms": 4.49,
      "avg_speed_ms": 1.73,
      "possession_s": 0.0,
      "passes_made": 0,
      "passes_received": 0,
      "interceptions": 0
    },
    "178": {
      "team": "Team B",
      "distance_m": 1.6,
      "top_speed_ms": 2.74,
      "avg_speed_ms": 1.48,
      "possession_s": 0.0,
      "passes_made": 0,
      "passes_received": 0,
      "interceptions": 0
    },
    "201": {
      "team": "Team B",
      "distance_m": 0.67,
      "top_speed_ms": 4.07,
      "avg_speed_ms": 2.8,
      "possession_s": 0.0,
      "passes_made": 0,
      "passes_received": 0,
      "interceptions": 0
    },
    "208": {
      "team": "Team B",
      "distance_m": 0.49,
      "top_speed_ms": 4.98,
      "avg_speed_ms": 4.12,
      "possession_s": 0.0,
      "passes_made": 0,
      "passes_received": 0,
      "interceptions": 0
    },
    "225": {
      "team": "Referee",
      "distance_m": 0.48,
      "top_speed_ms": 4.46,
      "avg_speed_ms": 3.96,
      "possession_s": 0.0,
      "passes_made": 0,
      "passes_received": 0,
      "interceptions": 0
    },
    "232": {
      "team": "Goalkeeper",
      "distance_m": 0.0,
      "top_speed_ms": 0.0,
      "avg_speed_ms": 0.0,
      "possession_s": 0.0,
      "passes_made": 0,
      "passes_received": 0,
      "interceptions": 0
    },
    "280": {
      "team": "Team A",
      "distance_m": 0.0,
      "top_speed_ms": 0.0,
      "avg_speed_ms": 0.0,
      "possession_s": 0.0,
      "passes_made": 0,
      "passes_received": 0,
      "interceptions": 0
    },
    "297": {
      "team": "Team B",
      "distance_m": 0.0,
      "top_speed_ms": 0.0,
      "avg_speed_ms": 0.0,
      "possession_s": 0.0,
      "passes_made": 0,
      "passes_received": 0,
      "interceptions": 0
    },
    "299": {
      "team": "Team A",
      "distance_m": 0.73,
      "top_speed_ms": 7.22,
      "avg_speed_ms": 6.1,
      "possession_s": 0.0,
      "passes_made": 0,
      "passes_received": 0,
      "interceptions": 0
    },
    "330": {
      "team": "Team A",
      "distance_m": 0.33,
      "top_speed_ms": 8.28,
      "avg_speed_ms": 8.28,
      "possession_s": 0.0,
      "passes_made": 0,
      "passes_received": 0,
      "interceptions": 0
    },
    "347": {
      "team": "Team A",
      "distance_m": 0.0,
      "top_speed_ms": 0.0,
      "avg_speed_ms": 0.0,
      "possession_s": 0.0,
      "passes_made": 0,
      "passes_received": 0,
      "interceptions": 0
    },
    "383": {
      "team": "Referee",
      "distance_m": 0.0,
      "top_speed_ms": 0.0,
      "avg_speed_ms": 0.0,
      "possession_s": 0.0,
      "passes_made": 0,
      "passes_received": 0,
      "interceptions": 0
    },
    "395": {
      "team": "Team A",
      "distance_m": 35.39,
      "top_speed_ms": 11.68,
      "avg_speed_ms": 4.27,
      "possession_s": 0.32,
      "passes_made": 1,
      "passes_received": 0,
      "interceptions": 1
    },
    "406": {
      "team": "Team A",
      "distance_m": 0.29,
      "top_speed_ms": 7.27,
      "avg_speed_ms": 7.27,
      "possession_s": 0.0,
      "passes_made": 0,
      "passes_received": 0,
      "interceptions": 0
    },
    "441": {
      "team": "Team A",
      "distance_m": 4.66,
      "top_speed_ms": 11.89,
      "avg_speed_ms": 5.06,
      "possession_s": 0.0,
      "passes_made": 0,
      "passes_received": 0,
      "interceptions": 0
    },
    "492": {
      "team": "Goalkeeper",
      "distance_m": 0.15,
      "top_speed_ms": 3.73,
      "avg_speed_ms": 1.87,
      "possession_s": 0.0,
      "passes_made": 0,
      "passes_received": 0,
      "interceptions": 0
    },
    "511": {
      "team": "Team A",
      "distance_m": 3.57,
      "top_speed_ms": 6.82,
      "avg_speed_ms": 3.31,
      "possession_s": 0.0,
      "passes_made": 0,
      "passes_received": 0,
      "interceptions": 0
    },
    "518": {
      "team": "Team B",
      "distance_m": 0.44,
      "top_speed_ms": 6.84,
      "avg_speed_ms": 5.44,
      "possession_s": 0.0,
      "passes_made": 0,
      "passes_received": 0,
      "interceptions": 0
    },
    "531": {
      "team": "Goalkeeper",
      "distance_m": 0.0,
      "top_speed_ms": 0.0,
      "avg_speed_ms": 0.0,
      "possession_s": 0.0,
      "passes_made": 0,
      "passes_received": 0,
      "interceptions": 0
    },
    "546": {
      "team": "Team B",
      "distance_m": 13.73,
      "top_speed_ms": 9.75,
      "avg_speed_ms": 4.58,
      "possession_s": 0.0,
      "passes_made": 0,
      "passes_received": 0,
      "interceptions": 0
    },
    "548": {
      "team": "Team B",
      "distance_m": 1.95,
      "top_speed_ms": 6.59,
      "avg_speed_ms": 2.87,
      "possession_s": 0.0,
      "passes_made": 0,
      "passes_received": 0,
      "interceptions": 0
    },
    "566": {
      "team": "Goalkeeper",
      "distance_m": 1.21,
      "top_speed_ms": 11.24,
      "avg_speed_ms": 5.03,
      "possession_s": 0.0,
      "passes_made": 0,
      "passes_received": 0,
      "interceptions": 0
    },
    "598": {
      "team": "Team A",
      "distance_m": 0.0,
      "top_speed_ms": 0.0,
      "avg_speed_ms": 0.0,
      "possession_s": 0.0,
      "passes_made": 0,
      "passes_received": 0,
      "interceptions": 0
    },
    "607": {
      "team": "Team A",
      "distance_m": 4.38,
      "top_speed_ms": 8.75,
      "avg_speed_ms": 1.69,
      "possession_s": 0.0,
      "passes_made": 0,
      "passes_received": 0,
      "interceptions": 0
    },
    "612": {
      "team": "Team A",
      "distance_m": 1.01,
      "top_speed_ms": 6.67,
      "avg_speed_ms": 5.07,
      "possession_s": 0.0,
      "passes_made": 0,
      "passes_received": 0,
      "interceptions": 0
    },
    "628": {
      "team": "Referee",
      "distance_m": 0.31,
      "top_speed_ms": 3.92,
      "avg_speed_ms": 3.83,
      "possession_s": 0.0,
      "passes_made": 0,
      "passes_received": 0,
      "interceptions": 0
    },
    "645": {
      "team": "Goalkeeper",
      "distance_m": 0.89,
      "top_speed_ms": 5.13,
      "avg_speed_ms": 4.43,
      "possession_s": 0.0,
      "passes_made": 0,
      "passes_received": 0,
      "interceptions": 0
    },
    "649": {
      "team": "Goalkeeper",
      "distance_m": 0.44,
      "top_speed_ms": 5.55,
      "avg_speed_ms": 1.85,
      "possession_s": 0.0,
      "passes_made": 0,
      "passes_received": 0,
      "interceptions": 0
    },
    "650": {
      "team": "Goalkeeper",
      "distance_m": 0.0,
      "top_speed_ms": 0.0,
      "avg_speed_ms": 0.0,
      "possession_s": 0.0,
      "passes_made": 0,
      "passes_received": 0,
      "interceptions": 0
    },
    "653": {
      "team": "Team B",
      "distance_m": 0.58,
      "top_speed_ms": 9.45,
      "avg_speed_ms": 7.27,
      "possession_s": 0.0,
      "passes_made": 0,
      "passes_received": 0,
      "interceptions": 0
    },
    "654": {
      "team": "Team A",
      "distance_m": 0.87,
      "top_speed_ms": 11.4,
      "avg_speed_ms": 10.83,
      "possession_s": 0.0,
      "passes_made": 0,
      "passes_received": 0,
      "interceptions": 0
    },
    "676": {
      "team": "Team A",
      "distance_m": 3.02,
      "top_speed_ms": 5.15,
      "avg_speed_ms": 1.89,
      "possession_s": 0.0,
      "passes_made": 0,
      "passes_received": 0,
      "interceptions": 0
    },
    "693": {
      "team": "Referee",
      "distance_m": 0.25,
      "top_speed_ms": 2.7,
      "avg_speed_ms": 2.04,
      "possession_s": 0.0,
      "passes_made": 0,
      "passes_received": 0,
      "interceptions": 0
    },
    "695": {
      "team": "Team A",
      "distance_m": 0.0,
      "top_speed_ms": 0.0,
      "avg_speed_ms": 0.0,
      "possession_s": 0.0,
      "passes_made": 0,
      "passes_received": 0,
      "interceptions": 0
    },
    "697": {
      "team": "Team A",
      "distance_m": 0.0,
      "top_speed_ms": 0.0,
      "avg_speed_ms": 0.0,
      "possession_s": 0.0,
      "passes_made": 0,
      "passes_received": 0,
      "interceptions": 0
    },
    "698": {
      "team": "Team B",
      "distance_m": 0.1,
      "top_speed_ms": 2.44,
      "avg_speed_ms": 2.44,
      "possession_s": 0.0,
      "passes_made": 0,
      "passes_received": 0,
      "interceptions": 0
    },
    "699": {
      "team": "Goalkeeper",
      "distance_m": 0.0,
      "top_speed_ms": 0.0,
      "avg_speed_ms": 0.0,
      "possession_s": 0.0,
      "passes_made": 0,
      "passes_received": 0,
      "interceptions": 0
    },
    "703": {
      "team": "Team A",
      "distance_m": 0.0,
      "top_speed_ms": 0.0,
      "avg_speed_ms": 0.0,
      "possession_s": 0.0,
      "passes_made": 0,
      "passes_received": 0,
      "interceptions": 0
    },
    "708": {
      "team": "Team A",
      "distance_m": 0.2,
      "top_speed_ms": 5.08,
      "avg_speed_ms": 5.08,
      "possession_s": 0.0,
      "passes_made": 0,
      "passes_received": 0,
      "interceptions": 0
    },
    "711": {
      "team": "Team B",
      "distance_m": 25.17,
      "top_speed_ms": 11.02,
      "avg_speed_ms": 4.25,
      "possession_s": 0.0,
      "passes_made": 0,
      "passes_received": 0,
      "interceptions": 0
    },
    "713": {
      "team": "Team B",
      "distance_m": 6.65,
      "top_speed_ms": 11.51,
      "avg_speed_ms": 4.05,
      "possession_s": 0.0,
      "passes_made": 0,
      "passes_received": 0,
      "interceptions": 0
    },
    "714": {
      "team": "Team A",
      "distance_m": 0.0,
      "top_speed_ms": 0.0,
      "avg_speed_ms": 0.0,
      "possession_s": 0.0,
      "passes_made": 0,
      "passes_received": 0,
      "interceptions": 0
    },
    "715": {
      "team": "Team B",
      "distance_m": 0.43,
      "top_speed_ms": 5.91,
      "avg_speed_ms": 5.4,
      "possession_s": 0.0,
      "passes_made": 0,
      "passes_received": 0,
      "interceptions": 0
    },
    "716": {
      "team": "Referee",
      "distance_m": 0.07,
      "top_speed_ms": 1.71,
      "avg_speed_ms": 1.71,
      "possession_s": 0.0,
      "passes_made": 0,
      "passes_received": 0,
      "interceptions": 0
    },
    "734": {
      "team": "Goalkeeper",
      "distance_m": 0.0,
      "top_speed_ms": 0.0,
      "avg_speed_ms": 0.0,
      "possession_s": 0.0,
      "passes_made": 0,
      "passes_received": 0,
      "interceptions": 0
    },
    "736": {
      "team": "Goalkeeper",
      "distance_m": 5.91,
      "top_speed_ms": 11.1,
      "avg_speed_ms": 6.43,
      "possession_s": 0.0,
      "passes_made": 0,
      "passes_received": 0,
      "interceptions": 0
    },
    "738": {
      "team": "Goalkeeper",
      "distance_m": 0.52,
      "top_speed_ms": 5.6,
      "avg_speed_ms": 3.26,
      "possession_s": 0.0,
      "passes_made": 0,
      "passes_received": 0,
      "interceptions": 0
    },
    "739": {
      "team": "Team A",
      "distance_m": 13.11,
      "top_speed_ms": 11.63,
      "avg_speed_ms": 6.43,
      "possession_s": 0.0,
      "passes_made": 0,
      "passes_received": 0,
      "interceptions": 0
    },
    "784": {
      "team": "Goalkeeper",
      "distance_m": 0.0,
      "top_speed_ms": 0.0,
      "avg_speed_ms": 0.0,
      "possession_s": 0.0,
      "passes_made": 0,
      "passes_received": 0,
      "interceptions": 0
    },
    "792": {
      "team": "Team B",
      "distance_m": 0.0,
      "top_speed_ms": 0.0,
      "avg_speed_ms": 0.0,
      "possession_s": 0.0,
      "passes_made": 0,
      "passes_received": 0,
      "interceptions": 0
    },
    "802": {
      "team": "Team A",
      "distance_m": 21.82,
      "top_speed_ms": 11.93,
      "avg_speed_ms": 6.57,
      "possession_s": 0.0,
      "passes_made": 0,
      "passes_received": 0,
      "interceptions": 0
    },
    "825": {
      "team": "Goalkeeper",
      "distance_m": 0.4,
      "top_speed_ms": 10.01,
      "avg_speed_ms": 10.01,
      "possession_s": 0.0,
      "passes_made": 0,
      "passes_received": 0,
      "interceptions": 0
    },
    "843": {
      "team": "Referee",
      "distance_m": 3.23,
      "top_speed_ms": 10.25,
      "avg_speed_ms": 6.72,
      "possession_s": 0.0,
      "passes_made": 0,
      "passes_received": 0,
      "interceptions": 0
    },
    "847": {
      "team": "Goalkeeper",
      "distance_m": 0.35,
      "top_speed_ms": 2.15,
      "avg_speed_ms": 1.73,
      "possession_s": 0.0,
      "passes_made": 0,
      "passes_received": 0,
      "interceptions": 0
    },
    "873": {
      "team": "Goalkeeper",
      "distance_m": 0.25,
      "top_speed_ms": 4.08,
      "avg_speed_ms": 3.07,
      "possession_s": 0.0,
      "passes_made": 0,
      "passes_received": 0,
      "interceptions": 0
    },
    "887": {
      "team": "Referee",
      "distance_m": 0.0,
      "top_speed_ms": 0.0,
      "avg_speed_ms": 0.0,
      "possession_s": 0.0,
      "passes_made": 0,
      "passes_received": 0,
      "interceptions": 0
    },
    "903": {
      "team": "Team B",
      "distance_m": 0.82,
      "top_speed_ms": 5.89,
      "avg_speed_ms": 4.08,
      "possession_s": 0.0,
      "passes_made": 0,
      "passes_received": 0,
      "interceptions": 0
    },
    "909": {
      "team": "Referee",
      "distance_m": 0.98,
      "top_speed_ms": 7.92,
      "avg_speed_ms": 6.11,
      "possession_s": 0.0,
      "passes_made": 0,
      "passes_received": 0,
      "interceptions": 0
    },
    "920": {
      "team": "Referee",
      "distance_m": 9.39,
      "top_speed_ms": 8.93,
      "avg_speed_ms": 4.89,
      "possession_s": 0.0,
      "passes_made": 0,
      "passes_received": 0,
      "interceptions": 0
    },
    "924": {
      "team": "Team A",
      "distance_m": 0.46,
      "top_speed_ms": 11.38,
      "avg_speed_ms": 11.38,
      "possession_s": 0.0,
      "passes_made": 0,
      "passes_received": 0,
      "interceptions": 0
    },
    "939": {
      "team": "Team A",
      "distance_m": 0.0,
      "top_speed_ms": 0.0,
      "avg_speed_ms": 0.0,
      "possession_s": 0.0,
      "passes_made": 0,
      "passes_received": 0,
      "interceptions": 0
    },
    "979": {
      "team": "Referee",
      "distance_m": 3.46,
      "top_speed_ms": 8.95,
      "avg_speed_ms": 5.09,
      "possession_s": 0.0,
      "passes_made": 0,
      "passes_received": 0,
      "interceptions": 0
    },
    "986": {
      "team": "Team A",
      "distance_m": 0.0,
      "top_speed_ms": 0.0,
      "avg_speed_ms": 0.0,
      "possession_s": 0.0,
      "passes_made": 0,
      "passes_received": 0,
      "interceptions": 0
    },
    "991": {
      "team": "Team B",
      "distance_m": 1.87,
      "top_speed_ms": 7.34,
      "avg_speed_ms": 6.67,
      "possession_s": 0.0,
      "passes_made": 0,
      "passes_received": 0,
      "interceptions": 0
    },
    "997": {
      "team": "Referee",
      "distance_m": 0.24,
      "top_speed_ms": 2.96,
      "avg_speed_ms": 1.97,
      "possession_s": 0.0,
      "passes_made": 0,
      "passes_received": 0,
      "interceptions": 0
    }
  },
  "per_team": {
    "Team A": {
      "players": 39,
      "total_distance_m": 1656.24,
      "possession_s": 13.0,
      "passes_made": 14,
      "passes_received": 5,
      "interceptions": 9
    },
    "Team B": {
      "players": 32,
      "total_distance_m": 966.32,
      "possession_s": 16.0,
      "passes_made": 26,
      "passes_received": 8,
      "interceptions": 18
    },
    "Goalkeeper": {
      "players": 20,
      "total_distance_m": 15.78,
      "possession_s": 0.0,
      "passes_made": 0,
      "passes_received": 0,
      "interceptions": 0
    }
  },
  "possession_seconds": {
    "Team A": 13.2,
    "Team B": 14.28
  },
  "total_passes": {
    "Team A": 14,
    "Team B": 26,
    "Goalkeeper": 0
  },
  "total_events": 40
}